{
  "env": "development",
  "service_name": "go-microservice",
  "grpc_port": 8881,
  "port": 8888,
  "db": "root:root@tcp(localhost:3306)/db_testing?charset=utf8&parseTime=True&charset=utf8mb4&collation=utf8mb4_unicode_ci",
  "authentication_secret_key": "",
  "authentication_pub_secret_key": "",
  "hash_key" :{
    "data_key": "se1041234567",
    "token_key": "se1041234567"
  },
  "kafka_brokers": "localhost:9092",
  "kafka_config":{
    "partitions": 3,
    "replication_factor": 1
  },
  "app_demo_ids": ["demo"]
}
